onconlp/__init__.py
onconlp/config.py
onconlp/core.py
onconlp-0.1.1.dist-info/METADATA
onconlp-0.1.1.dist-info/WHEEL
onconlp-0.1.1.dist-info/top_level.txt
onconlp-0.1.1.dist-info/RECORD
