Metadata-Version: 2.4
Name: onconlp
Version: 0.1.1
Summary: Natural Language Processing Toolkit for Oncology
Home-page: https://github.com/onconlp/onconlp
Author: OncoNLP Development Team
Author-email: OncoNLP Development Team <team@onconlp.org>
License: MIT
Project-URL: Homepage, https://github.com/onconlp/onconlp
Project-URL: Documentation, https://onconlp.readthedocs.io/
Project-URL: Repository, https://github.com/onconlp/onconlp
Project-URL: Bug Reports, https://github.com/onconlp/onconlp/issues
Keywords: oncology,nlp,medical,text-processing,cancer-research
Classifier: Development Status :: 3 - Alpha
Classifier: Intended Audience :: Healthcare Industry
Classifier: Intended Audience :: Science/Research
Classifier: Topic :: Scientific/Engineering :: Medical Science Apps.
Classifier: Topic :: Text Processing :: Linguistic
Classifier: License :: OSI Approved :: MIT License
Classifier: Programming Language :: Python :: 3
Classifier: Programming Language :: Python :: 3.8
Classifier: Programming Language :: Python :: 3.9
Classifier: Programming Language :: Python :: 3.10
Classifier: Programming Language :: Python :: 3.11
Classifier: Programming Language :: Python :: 3.12
Classifier: Operating System :: OS Independent
Requires-Python: >=3.8
Requires-Dist: numpy>=1.21.0
Requires-Dist: pandas>=1.3.0
Requires-Dist: regex>=2022.7.0
Dynamic: author
Dynamic: home-page
Dynamic: requires-python
